ameisedataset/__init__.py
ameisedataset/core.py
ameisedataset/data/__init__.py
ameisedataset/data/agent.py
ameisedataset/data/data.py
ameisedataset/data/frame.py
ameisedataset/data/metadata.py
ameisedataset/data/names.py
ameisedataset/data/sensors.py
ameisedataset/miscellaneous/__init__.py
ameisedataset/miscellaneous/contstants.py
ameisedataset/miscellaneous/error_exceptions.py
ameisedataset/miscellaneous/helper.py
ameisedataset/utils/__init__.py
ameisedataset/utils/image_functions.py
ameisedataset/utils/transformation.py
ameisedataset/utils/transformation_old.py
ameisedataset/utils/visualisation.py
ameise-0.5.2.dist-info/LICENSE
ameise-0.5.2.dist-info/METADATA
ameise-0.5.2.dist-info/WHEEL
ameise-0.5.2.dist-info/top_level.txt
ameise-0.5.2.dist-info/RECORD
