Metadata-Version: 2.1
Name: ameise
Version: 0.5.2
Summary: Dev-Kit for AMEISE dataset
Home-page: https://github.com/MarcelVSHNS/ameise-dataset.git
Author: Marcel
Author-email: marcel.vosshans@hs-esslingen.de
License: Apache License 2.0
Platform: UNKNOWN
Requires-Python: >=3.7
Requires-Dist: Pillow
Requires-Dist: datetime
Requires-Dist: dill
Requires-Dist: numpy
